faceclient/__init__.py
faceclient/api.py
faceclient/base.py
faceclient/faces.py
faceclient/httpclient.py
face_server_client-0.0.6.dist-info/AUTHORS
face_server_client-0.0.6.dist-info/METADATA
face_server_client-0.0.6.dist-info/WHEEL
face_server_client-0.0.6.dist-info/entry_points.txt
face_server_client-0.0.6.dist-info/pbr.json
face_server_client-0.0.6.dist-info/top_level.txt
face_server_client-0.0.6.dist-info/RECORD
