Metadata-Version: 2.1
Name: face-server-client
Version: 0.0.6
Summary: Face server Client Library
Home-page: UNKNOWN
Author: KuberLab
License: Apache Software License
Platform: UNKNOWN
Classifier: Programming Language :: Python
Classifier: Programming Language :: Python :: 3
Classifier: Programming Language :: Python :: 3.5
Classifier: Programming Language :: Python :: 3.6
Classifier: Programming Language :: Python :: 3.7
Classifier: Programming Language :: Python :: 3.8
Classifier: Intended Audience :: Information Technology
Classifier: Intended Audience :: System Administrators
Classifier: License :: OSI Approved :: Apache Software License
Classifier: Operating System :: POSIX :: Linux
Requires-Dist: opencv-python
Requires-Dist: pbr (!=2.1.0,>=2.0.0)
Requires-Dist: requests (>=2.14.2)
